electrostaticvacuum/__init__.py
electrostaticvacuum/electrostatic_field.py
electrostaticvacuum/field.py
electrostaticvacuum/point_charge.py
electrostaticvacuum/positioned.py
electrostaticvacuum/vector.py
electrostaticvacuum-1.1.dist-info/LICENSE
electrostaticvacuum-1.1.dist-info/METADATA
electrostaticvacuum-1.1.dist-info/WHEEL
electrostaticvacuum-1.1.dist-info/top_level.txt
electrostaticvacuum-1.1.dist-info/RECORD
